FactScoreLite/__init__.py
FactScoreLite/atomic_facts.py
FactScoreLite/configs.py
FactScoreLite/fact_scorer.py
FactScoreLite/factscore.py
FactScoreLite/openai_agent.py
FactScoreLite/state_handler.py
FactScoreLite/data/atomic_facts_demons.json
FactScoreLite/data/demons_generation_prompt.txt
FactScoreLite/data/fact_scorer_demons.json
tests/__init__.py
tests/test_atomic_facts.py
tests/test_fact_scorer.py
tests/test_factscore.py
tests/test_openai_agent.py
tests/test_state_handler.py
FactScoreLite-1.3.0.dist-info/LICENSE
FactScoreLite-1.3.0.dist-info/METADATA
FactScoreLite-1.3.0.dist-info/WHEEL
FactScoreLite-1.3.0.dist-info/top_level.txt
FactScoreLite-1.3.0.dist-info/RECORD
