Metadata-Version: 2.1
Name: FactScoreLite
Version: 1.3.0
Summary: FactScore (Fine-grained atomic evaluation of factual precision in long form text generation) computing package.
Home-page: https://github.com/armingh2000/FactScoreLite
Author: armingh2000
Author-email: 
License: MIT
Classifier: Programming Language :: Python :: 3
Classifier: License :: OSI Approved :: MIT License
Classifier: Operating System :: OS Independent
License-File: LICENSE
Requires-Dist: numpy
Requires-Dist: nltk
Requires-Dist: openai
Requires-Dist: pytest
Requires-Dist: pytest-mock
